python_mecab_ner/__init__.py
python_mecab_ner/mecab_ner.py
python_mecab_ner/mecab_parser.py
python_mecab_ner/mecab_reader.py
python_mecab_ner/mecab_storage.py
python_mecab_ner/data/ner_data/body.txt
python_mecab_ner/data/ner_data/fastfood.txt
python_mecab_ner/data/ner_data/fruit.txt
python_mecab_ner/data/ner_data/location_country.txt
python_mecab_ner/data/ner_data/location_tour.txt
python_mecab_ner/data/ner_data/music_singer.txt
python_mecab_ner/data/ner_data/music_song.txt
python_mecab_ner/data/ner_data/ner_example_body.txt
python_mecab_ner/data/ner_data/ner_example_fastfood.txt
python_mecab_ner/data/ner_data/ner_example_fruit.txt
python_mecab_ner/data/ner_data/ner_example_location_country.txt
python_mecab_ner/data/ner_data/ner_example_location_tour.txt
python_mecab_ner/data/ner_data/ner_example_music_singer.txt
python_mecab_ner/data/ner_data/ner_example_music_song.txt
python_mecab_ner/domain/mecab_domain.py
python_mecab_ner/domain/mecab_exception.py
python_mecab_ner/service/mecab_parser.py
python_mecab_ner/service/mecab_reader.py
python_mecab_ner/service/mecab_storage.py
python_mecab_ner-1.0.8.dist-info/LICENSE
python_mecab_ner-1.0.8.dist-info/METADATA
python_mecab_ner-1.0.8.dist-info/WHEEL
python_mecab_ner-1.0.8.dist-info/top_level.txt
python_mecab_ner-1.0.8.dist-info/RECORD
