Metadata-Version: 2.1
Name: python-mecab-ner
Version: 1.0.8
Summary: Test package for distribution
Home-page: https://github.com/YoungchanChang/python-mecab-ner
Download-URL: 
Author: Youngchan
Author-email: gamsunghacker@gmail.com
License: UNKNOWN
Keywords: Text Processing,Text Processing :: Linguistic,NER,mecab,mecab-ko,mecab-ner
Platform: UNKNOWN
Classifier: Programming Language :: Python :: 3
Classifier: Programming Language :: Python :: 3 :: Only
Classifier: License :: OSI Approved :: MIT License
Classifier: Intended Audience :: Science/Research
Classifier: Natural Language :: Korean
Classifier: Operating System :: OS Independent
Requires-Python: >=3.7
License-File: LICENSE
Requires-Dist: pybind11 (~=2.0)
Requires-Dist: python-mecab-ko (~=1.0.12)
